odoo/addons/purchase_fully_invoiced/README.rst
odoo/addons/purchase_fully_invoiced/__init__.py
odoo/addons/purchase_fully_invoiced/__manifest__.py
odoo/addons/purchase_fully_invoiced/i18n/it.po
odoo/addons/purchase_fully_invoiced/i18n/purchase_fully_invoiced.pot
odoo/addons/purchase_fully_invoiced/models/__init__.py
odoo/addons/purchase_fully_invoiced/models/purchase.py
odoo/addons/purchase_fully_invoiced/readme/CONTRIBUTORS.rst
odoo/addons/purchase_fully_invoiced/readme/DESCRIPTION.rst
odoo/addons/purchase_fully_invoiced/readme/USAGE.rst
odoo/addons/purchase_fully_invoiced/static/description/icon.png
odoo/addons/purchase_fully_invoiced/static/description/index.html
odoo/addons/purchase_fully_invoiced/tests/__init__.py
odoo/addons/purchase_fully_invoiced/tests/test_purchase_fully_invoiced.py
odoo/addons/purchase_fully_invoiced/views/purchase_views.xml
odoo_addon_purchase_fully_invoiced-16.0.1.0.0.5.dist-info/METADATA
odoo_addon_purchase_fully_invoiced-16.0.1.0.0.5.dist-info/WHEEL
odoo_addon_purchase_fully_invoiced-16.0.1.0.0.5.dist-info/top_level.txt
odoo_addon_purchase_fully_invoiced-16.0.1.0.0.5.dist-info/RECORD
