Metadata-Version: 2.1
Name: odoo-addon-purchase_fully_invoiced
Version: 16.0.1.0.0.5
Summary: Useful filters in Purchases to know the actual status of invoices.
Home-page: https://github.com/OCA/purchase-workflow
Author: Forgeflow, Odoo Community Association (OCA)
Author-email: support@odoo-community.org
License: AGPL-3
Classifier: Programming Language :: Python
Classifier: Framework :: Odoo
Classifier: Framework :: Odoo :: 16.0
Classifier: License :: OSI Approved :: GNU Affero General Public License v3
Requires-Python: >=3.10
Requires-Dist: odoo<16.1dev,>=16.0a
